{
  "version": "2.0",
  "logging": {
    "applicationInsights": {
      "samplingSettings": {
        "isEnabled": true,
        "excludedTypes": "Request"
      },
      "enableLiveMetricsFilters": true
    },
    "logLevel": {
      "default": "Information",
      "Host.Results": "Information",
      "Function": "Information"
    }
  },
  "extensions": {
    "queues": {
      "maxPollingInterval": "00:00:05",
      "batchSize": 16,
      "maxDequeueCount": 5,
      "newBatchThreshold": 8,
      "visibilityTimeout": "00:05:00"
    },
    "blobs": {
      "maxDegreeOfParallelism": 8
    }
  },
  "functionTimeout": "00:10:00",
  "extensionBundle": {
    "id": "Microsoft.Azure.Functions.ExtensionBundle",
    "version": "[4.*, 5.0.0)"
  }
}
